{"ocrEngine":{"enabled":false,"roleAccess":{"user":false},"lastUpdated":"2026-06-23T14:41:03.986Z","capabilities":{"transactionOCR":{"enabled":false,"roleAccess":{"user":false}}}},"voiceAssistant":{"enabled":false,"roleAccess":{"user":false},"lastUpdated":"2026-06-23T14:41:03.986Z","capabilities":{}},"aiAutomation":{"enabled":false,"roleAccess":{"user":false},"lastUpdated":"2026-06-23T14:41:03.986Z","capabilities":{"smartCategorization":{"enabled":false,"roleAccess":{"user":false}},"subscriptionDetection":{"enabled":false,"roleAccess":{"user":false}},"healthScoring":{"enabled":false,"roleAccess":{"user":false}},"anomalyDetection":{"enabled":false,"roleAccess":{"user":false}}}}}